{
  "schema_version": 1,
  "group": "lorenz_partial_25d_additive_gennmse__lc_sweep",
  "analyzed_at": "2026-04-14T16:42:25Z",
  "metrics_summary": {
    "per_run": [
      {
        "run_id": "fxb2ugkx",
        "state": "finished",
        "lc_weight": 0.0,
        "obs_noise_scale": 0.0,
        "best_traj_loss": 5.9504662203835323e-05,
        "best_traj_loss_epoch": 159.0,
        "best_mase": 0.051063843071460724,
        "best_mase_epoch": 163.0,
        "lc_loss_at_best_tl": 1.79814875125885,
        "r2_at_best_tl": 0.9999313950538635,
        "n_epochs": 168
      },
      {
        "run_id": "8ymb10x8",
        "state": "finished",
        "lc_weight": 1e-06,
        "obs_noise_scale": 0.0,
        "best_traj_loss": 5.9332236560294405e-05,
        "best_traj_loss_epoch": 159.0,
        "best_mase": 0.05175989493727684,
        "best_mase_epoch": 157.0,
        "lc_loss_at_best_tl": 1.1350761651992798,
        "r2_at_best_tl": 0.9999316930770874,
        "n_epochs": 168
      },
      {
        "run_id": "n9kvy1ms",
        "state": "finished",
        "lc_weight": 1e-05,
        "obs_noise_scale": 0.0,
        "best_traj_loss": 5.63506328035146e-05,
        "best_traj_loss_epoch": 197.0,
        "best_mase": 0.04724783077836037,
        "best_mase_epoch": 198.0,
        "lc_loss_at_best_tl": 0.20183616876602173,
        "r2_at_best_tl": 0.9999347925186157,
        "n_epochs": 200
      },
      {
        "run_id": "rl5389n9",
        "state": "finished",
        "lc_weight": 0.0001,
        "obs_noise_scale": 0.0,
        "best_traj_loss": 6.914730329299346e-05,
        "best_traj_loss_epoch": 159.0,
        "best_mase": 0.05411604046821594,
        "best_mase_epoch": 163.0,
        "lc_loss_at_best_tl": 0.03722800314426422,
        "r2_at_best_tl": 0.9999199509620667,
        "n_epochs": 169
      },
      {
        "run_id": "uup45vfy",
        "state": "finished",
        "lc_weight": 0.001,
        "obs_noise_scale": 0.0,
        "best_traj_loss": 8.641776366857812e-05,
        "best_traj_loss_epoch": 198.0,
        "best_mase": 0.062311992049217224,
        "best_mase_epoch": 198.0,
        "lc_loss_at_best_tl": 0.003357512876391411,
        "r2_at_best_tl": 0.9998998045921326,
        "n_epochs": 200
      },
      {
        "run_id": "94fg726v",
        "state": "finished",
        "lc_weight": 0.01,
        "obs_noise_scale": 0.0,
        "best_traj_loss": 0.00011430896847741678,
        "best_traj_loss_epoch": 192.0,
        "best_mase": 0.08601584285497665,
        "best_mase_epoch": 187.0,
        "lc_loss_at_best_tl": 0.0006207296391949058,
        "r2_at_best_tl": 0.9998675584793091,
        "n_epochs": 200
      },
      {
        "run_id": "7eknb3d1",
        "state": "finished",
        "lc_weight": 0.1,
        "obs_noise_scale": 0.0,
        "best_traj_loss": 0.000140458854730241,
        "best_traj_loss_epoch": 166.0,
        "best_mase": 0.10859981179237366,
        "best_mase_epoch": 198.0,
        "lc_loss_at_best_tl": 4.876431921729818e-05,
        "r2_at_best_tl": 0.999838650226593,
        "n_epochs": 200
      },
      {
        "run_id": "cmhou3ak",
        "state": "finished",
        "lc_weight": 1.0,
        "obs_noise_scale": 0.0,
        "best_traj_loss": 0.00012571370461955667,
        "best_traj_loss_epoch": 198.0,
        "best_mase": 0.10620181262493134,
        "best_mase_epoch": 199.0,
        "lc_loss_at_best_tl": 9.458739441470243e-06,
        "r2_at_best_tl": 0.9998549818992615,
        "n_epochs": 200
      },
      {
        "run_id": "i257bznv",
        "state": "finished",
        "lc_weight": 10.0,
        "obs_noise_scale": 0.0,
        "best_traj_loss": 0.00012630168930627406,
        "best_traj_loss_epoch": 199.0,
        "best_mase": 0.11989978700876236,
        "best_mase_epoch": 191.0,
        "lc_loss_at_best_tl": 1.9170552150171716e-06,
        "r2_at_best_tl": 0.9998531937599182,
        "n_epochs": 200
      }
    ],
    "best_by_obs_noise_scale": {
      "0.0": {
        "run_id": "n9kvy1ms",
        "state": "finished",
        "lc_weight": 1e-05,
        "obs_noise_scale": 0.0,
        "best_traj_loss": 5.63506328035146e-05,
        "best_traj_loss_epoch": 197.0,
        "best_mase": 0.04724783077836037,
        "best_mase_epoch": 198.0,
        "lc_loss_at_best_tl": 0.20183616876602173,
        "r2_at_best_tl": 0.9999347925186157,
        "n_epochs": 200
      }
    },
    "overall_best_mase": {
      "run_id": "n9kvy1ms",
      "state": "finished",
      "lc_weight": 1e-05,
      "obs_noise_scale": 0.0,
      "best_traj_loss": 5.63506328035146e-05,
      "best_traj_loss_epoch": 197.0,
      "best_mase": 0.04724783077836037,
      "best_mase_epoch": 198.0,
      "lc_loss_at_best_tl": 0.20183616876602173,
      "r2_at_best_tl": 0.9999347925186157,
      "n_epochs": 200
    },
    "n_runs": 9
  },
  "per_run_lyapunov": {
    "fxb2ugkx": {
      "lambda_spectrum": [
        0.22649216651916504,
        -0.7386903762817383,
        -14.417399406433105
      ],
      "lambda_max": 0.22649216651916504,
      "lambda_sum": -14.929597854614258,
      "kaplan_yorke_dim": 1.3066130876541138,
      "error": null,
      "spectrum_mse_vs_true": 0.2694751022550968
    },
    "8ymb10x8": {
      "lambda_spectrum": [
        0.2276114672422409,
        -0.7742560505867004,
        -14.759371757507324
      ],
      "lambda_max": 0.2276114672422409,
      "lambda_sum": -15.306015968322754,
      "kaplan_yorke_dim": 1.2939743995666504,
      "error": null,
      "spectrum_mse_vs_true": 0.44523622937379814
    },
    "n9kvy1ms": {
      "lambda_spectrum": [
        0.1994500756263733,
        -0.7256811261177063,
        -15.641453742980957
      ],
      "lambda_max": 0.1994500756263733,
      "lambda_sum": -16.16768455505371,
      "kaplan_yorke_dim": 1.2748453617095947,
      "error": null,
      "spectrum_mse_vs_true": 1.1889915388793022
    },
    "rl5389n9": {
      "lambda_spectrum": [
        0.2951372563838959,
        -0.8461928367614746,
        -17.065248489379883
      ],
      "lambda_max": 0.2951372563838959,
      "lambda_sum": -17.616304397583008,
      "kaplan_yorke_dim": 1.3487825393676758,
      "error": null,
      "spectrum_mse_vs_true": 3.585459328894618
    },
    "uup45vfy": {
      "lambda_spectrum": [
        0.24120062589645386,
        -0.9602311253547668,
        -17.16840362548828
      ],
      "lambda_max": 0.24120062589645386,
      "lambda_sum": -17.887434005737305,
      "kaplan_yorke_dim": 1.251190185546875,
      "error": null,
      "spectrum_mse_vs_true": 3.8739688521817417
    },
    "94fg726v": {
      "lambda_spectrum": [
        0.19470739364624023,
        -0.7720153331756592,
        -18.051219940185547
      ],
      "lambda_max": 0.19470739364624023,
      "lambda_sum": -18.628528594970703,
      "kaplan_yorke_dim": 1.2522066831588745,
      "error": null,
      "spectrum_mse_vs_true": 5.952755411709752
    },
    "7eknb3d1": {
      "lambda_spectrum": [
        0.284091591835022,
        -0.7104102969169617,
        -14.48560619354248
      ],
      "lambda_max": 0.284091591835022,
      "lambda_sum": -14.911925315856934,
      "kaplan_yorke_dim": 1.3998979330062866,
      "error": null,
      "spectrum_mse_vs_true": 0.28200269841778663
    },
    "cmhou3ak": {
      "lambda_spectrum": [
        0.4519965648651123,
        -1.1259636878967285,
        -12.458149909973145
      ],
      "lambda_max": 0.4519965648651123,
      "lambda_sum": -13.13211727142334,
      "kaplan_yorke_dim": 1.4014308452606201,
      "error": null,
      "spectrum_mse_vs_true": 1.1218516716836093
    },
    "i257bznv": {
      "lambda_spectrum": [
        0.46723294258117676,
        -1.6393874883651733,
        -14.05461597442627
      ],
      "lambda_max": 0.46723294258117676,
      "lambda_sum": -15.226770401000977,
      "kaplan_yorke_dim": 1.2850046157836914,
      "error": null,
      "spectrum_mse_vs_true": 0.9150085481105571
    }
  },
  "empirical_lyapunov_spectrum": [
    0.2350996732711792,
    -0.00666311988607049,
    -13.89539623260498
  ],
  "per_run_lyapunov_error": null,
  "success_criteria_verdicts": [
    {
      "criterion": "Best run's leading Lyapunov exponent > 0 (chaos recovered)",
      "verdict": "Unknown",
      "note": ""
    },
    {
      "criterion": "Best run's predicted Lyapunov spectrum within ~30% of empirical",
      "verdict": "Unknown",
      "note": ""
    },
    {
      "criterion": "Best run's free-running sliced-Wasserstein-1 to training data distribution is low (sanity: obs histograms overlap)",
      "verdict": "Unknown",
      "note": ""
    },
    {
      "criterion": "val/trajectory_r2_score > 0.9 at the best configuration",
      "verdict": "Pass",
      "note": "Best R\u00b2 = 0.9999; threshold > 0.9"
    },
    {
      "criterion": "Loop closure bounded and monotonically improving at low LC",
      "verdict": "Unknown",
      "note": ""
    }
  ],
  "figures": {
    "sweep_overview": "/orcd/data/ekmiller/001/eisenaj/JacobianODE/sweeps/analysis/lorenz_partial_25d_additive_gennmse__lc_sweep/figures/sweep_overview.png",
    "sweep_pareto": "/orcd/data/ekmiller/001/eisenaj/JacobianODE/sweeps/analysis/lorenz_partial_25d_additive_gennmse__lc_sweep/figures/sweep_pareto.png",
    "mase": "/orcd/data/ekmiller/001/eisenaj/JacobianODE/sweeps/analysis/lorenz_partial_25d_additive_gennmse__lc_sweep/figures/mase.png",
    "lyapunov": "/orcd/data/ekmiller/001/eisenaj/JacobianODE/sweeps/analysis/lorenz_partial_25d_additive_gennmse__lc_sweep/figures/lyapunov.png",
    "prediction_windows": "/orcd/data/ekmiller/001/eisenaj/JacobianODE/sweeps/analysis/lorenz_partial_25d_additive_gennmse__lc_sweep/figures/prediction_windows.png",
    "per_run_lyapunov": "/orcd/data/ekmiller/001/eisenaj/JacobianODE/sweeps/analysis/lorenz_partial_25d_additive_gennmse__lc_sweep/figures/per_run_lyapunov.png",
    "per_run_lyapunov_vs_true": "/orcd/data/ekmiller/001/eisenaj/JacobianODE/sweeps/analysis/lorenz_partial_25d_additive_gennmse__lc_sweep/figures/per_run_lyapunov_vs_true.png",
    "lyapunov_spectrum_mse_vs_val_loss": "/orcd/data/ekmiller/001/eisenaj/JacobianODE/sweeps/analysis/lorenz_partial_25d_additive_gennmse__lc_sweep/figures/lyapunov_spectrum_mse_vs_val_loss.png"
  },
  "analytics_error": null,
  "true_lyapunov": null,
  "analytics_log_file": "run_analytics.log"
}
